inventory/__init__.py
inventory/apps.py
inventory/checks.py
inventory/ckeditor_upload.py
inventory/constants.py
inventory/context_processors.py
inventory/forms.py
inventory/middlewares.py
inventory/parent_tree.py
inventory/permissions.py
inventory/persistent_filters.py
inventory/request_dict.py
inventory/signals.py
inventory/string_utils.py
inventory/admin/__init__.py
inventory/admin/base.py
inventory/admin/item.py
inventory/admin/location.py
inventory/admin/memo.py
inventory/admin/tagulous_fix.py
inventory/locale/ca/LC_MESSAGES/django.mo
inventory/locale/ca/LC_MESSAGES/django.po
inventory/locale/de/LC_MESSAGES/django.mo
inventory/locale/de/LC_MESSAGES/django.po
inventory/locale/en/LC_MESSAGES/django.mo
inventory/locale/en/LC_MESSAGES/django.po
inventory/locale/es/LC_MESSAGES/django.mo
inventory/locale/es/LC_MESSAGES/django.po
inventory/management/__init__.py
inventory/management/commands/__init__.py
inventory/management/commands/seed_data.py
inventory/management/commands/tree.py
inventory/migrations/0001_initial.py
inventory/migrations/0002_auto_20201017_2211.py
inventory/migrations/0003_auto_20201024_1830.py
inventory/migrations/0004_item_user_images.py
inventory/migrations/0005_serve_uploads_by_django_tools.py
inventory/migrations/0006_refactor_image_model.py
inventory/migrations/0007_add_file_attachment.py
inventory/migrations/0008_last_check_datetime.py
inventory/migrations/0009_add_memo.py
inventory/migrations/0010_version_protect_models.py
inventory/migrations/0011_parent_tree1.py
inventory/migrations/0012_parent_tree2.py
inventory/migrations/0013_alter_itemmodel_location.py
inventory/migrations/0014_alter_itemmodel_description_and_more.py
inventory/migrations/0015_itemmaincategory_itemmodel_category.py
inventory/migrations/__init__.py
inventory/models/__init__.py
inventory/models/base.py
inventory/models/item.py
inventory/models/links.py
inventory/models/location.py
inventory/models/memo.py
inventory/templates/admin/item/related_items.html
pyinventory-0.22.0.dist-info/METADATA
pyinventory-0.22.0.dist-info/WHEEL
pyinventory-0.22.0.dist-info/entry_points.txt
pyinventory-0.22.0.dist-info/licenses/AUTHORS
pyinventory-0.22.0.dist-info/licenses/LICENSE
pyinventory-0.22.0.dist-info/RECORD
