Metadata-Version: 2.4
Name: PyInventory
Version: 0.22.0
Summary: Web based management to catalog things including state and location etc. using Python/Django.
Project-URL: Documentation, https://github.com/jedie/PyInventory
Project-URL: Source, https://github.com/jedie/PyInventory
Author-email: Jens Diemer <PyInventory@jensdiemer.de>
License: GPL-3.0-or-later
License-File: AUTHORS
License-File: LICENSE
Keywords: django,inventory
Requires-Python: >=3.11
Requires-Dist: bx-django-utils
Requires-Dist: bx-py-utils
Requires-Dist: colorlog
Requires-Dist: django-admin-sortable2
Requires-Dist: django-axes
Requires-Dist: django-dbbackup
Requires-Dist: django-debug-toolbar
Requires-Dist: django-import-export
Requires-Dist: django-reversion-compare
Requires-Dist: django-tagulous
Requires-Dist: django-tinymce
Requires-Dist: django-tools
Requires-Dist: django<5.2,>5.1
Requires-Dist: gunicorn
Requires-Dist: pillow
Requires-Dist: requests
